allama/__init__.py
allama/allama.py
allama/config_loader.py
allama/evaluator.py
allama/main.py
allama/open_report.py
allama/publisher.py
allama/report_generator.py
allama/static/css/allama-charts.css
allama/static/js/radar-chart.js
allama/static/templates/stats-badges.html
allama/templates/report_template.html
allama-0.1.18.dist-info/LICENSE
allama-0.1.18.dist-info/METADATA
allama-0.1.18.dist-info/WHEEL
allama-0.1.18.dist-info/entry_points.txt
allama-0.1.18.dist-info/RECORD
